neuron_memory/__init__.py
neuron_memory/config.py
neuron_memory/api/__init__.py
neuron_memory/api/neuron_memory_api.py
neuron_memory/core/__init__.py
neuron_memory/core/memory_manager.py
neuron_memory/core/memory_store.py
neuron_memory/core/retrieval_engine.py
neuron_memory/llm/__init__.py
neuron_memory/llm/azure_openai_client.py
neuron_memory/memory/__init__.py
neuron_memory/memory/memory_objects.py
neuron_memory-0.1.6.dist-info/METADATA
neuron_memory-0.1.6.dist-info/WHEEL
neuron_memory-0.1.6.dist-info/entry_points.txt
neuron_memory-0.1.6.dist-info/top_level.txt
neuron_memory-0.1.6.dist-info/RECORD
