Metadata-Version: 2.4
Name: neuron-memory
Version: 0.1.6
Summary: Advanced Memory Engine for LLMs and AI Agents
Home-page: https://github.com/NeuronMemory/neuronmemory
Author: NeuronMemory Team
Author-email: danushidk507@gmail.com
Classifier: Development Status :: 3 - Alpha
Classifier: Intended Audience :: Developers
Classifier: License :: OSI Approved :: MIT License
Classifier: Operating System :: OS Independent
Classifier: Programming Language :: Python :: 3
Classifier: Programming Language :: Python :: 3.8
Classifier: Programming Language :: Python :: 3.9
Classifier: Programming Language :: Python :: 3.10
Classifier: Programming Language :: Python :: 3.11
Requires-Python: >=3.8
Requires-Dist: openai
Requires-Dist: numpy
Requires-Dist: pandas
Requires-Dist: scipy
Requires-Dist: scikit-learn
Requires-Dist: chromadb
Requires-Dist: lancedb
Requires-Dist: faiss-cpu
Requires-Dist: qdrant-client
Requires-Dist: sentence-transformers
Requires-Dist: transformers
Requires-Dist: nltk
Requires-Dist: spacy
Requires-Dist: asyncio
Requires-Dist: aiohttp
Requires-Dist: redis
Requires-Dist: celery
Requires-Dist: pydantic
Requires-Dist: pydantic-settings
Requires-Dist: python-dotenv
Requires-Dist: jsonschema
Requires-Dist: networkx
Requires-Dist: pygraphviz
Requires-Dist: loguru
Requires-Dist: prometheus-client
Requires-Dist: psutil
Requires-Dist: pytest
Requires-Dist: pytest-asyncio
Requires-Dist: pytest-mock
Requires-Dist: black
Requires-Dist: isort
Requires-Dist: mypy
Requires-Dist: fastapi
Requires-Dist: uvicorn
Requires-Dist: python-dateutil
Requires-Dist: uuid
Requires-Dist: hashlib
Requires-Dist: typing-extensions
Provides-Extra: dev
Requires-Dist: pytest>=7.4.0; extra == "dev"
Requires-Dist: pytest-asyncio>=0.21.0; extra == "dev"
Requires-Dist: black>=23.7.0; extra == "dev"
Requires-Dist: isort>=5.12.0; extra == "dev"
Requires-Dist: mypy>=1.5.0; extra == "dev"
Provides-Extra: full
Requires-Dist: weaviate-client>=3.24.0; extra == "full"
Requires-Dist: pinecone-client>=2.2.0; extra == "full"
Requires-Dist: elasticsearch>=8.9.0; extra == "full"
Dynamic: author
Dynamic: author-email
Dynamic: classifier
Dynamic: description
Dynamic: description-content-type
Dynamic: home-page
Dynamic: provides-extra
Dynamic: requires-dist
Dynamic: requires-python
Dynamic: summary
